lomond/__init__.py
lomond/_version.py
lomond/compression.py
lomond/constants.py
lomond/errors.py
lomond/events.py
lomond/extension.py
lomond/frame.py
lomond/frame_parser.py
lomond/mask.py
lomond/message.py
lomond/opcode.py
lomond/parser.py
lomond/persist.py
lomond/proxy.py
lomond/response.py
lomond/selectors.py
lomond/session.py
lomond/status.py
lomond/stream.py
lomond/utf8validator.py
lomond/websocket.py
lomond/examples/__init__.py
lomond/examples/btcticker.py
lomond/examples/chat.py
lomond/examples/chatserver.py
lomond-0.3.3.dist-info/METADATA
lomond-0.3.3.dist-info/RECORD
lomond-0.3.3.dist-info/WHEEL
lomond-0.3.3.dist-info/top_level.txt
lomond-0.3.3.dist-info/zip-safe
