Metadata-Version: 2.1
Name: lomond
Version: 0.3.3
Summary: Websocket Client Library
Home-page: https://github.com/wildfoundry/dataplicity-lomond
Author: WildFoundry
Author-email: willmcgugan@gmail.com
License: UNKNOWN
Platform: any
Classifier: Development Status :: 5 - Production/Stable
Classifier: Intended Audience :: Developers
Classifier: Programming Language :: Python
Classifier: License :: OSI Approved :: BSD License
Classifier: Programming Language :: Python :: 2.7
Classifier: Programming Language :: Python :: 3.3
Classifier: Programming Language :: Python :: 3.4
Classifier: Programming Language :: Python :: 3.5
Classifier: Programming Language :: Python :: 3.6
Classifier: Topic :: Internet
